{
    "created_time": "2022-12-31T10:17:57Z",
    "files": [
        {
            "attachment_folder": "",
            "created_time": "2022-12-31T10:17:57Z",
            "id": "20194",
            "modified_time": "2022-12-31T10:17:57Z",
            "name": "Go中的Scheme解析器.md",
            "signature": "77302493875285",
            "tags": [
            ]
        },
        {
            "attachment_folder": "",
            "created_time": "2022-12-31T10:17:57Z",
            "id": "20195",
            "modified_time": "2022-12-31T10:17:57Z",
            "name": "MIT-Scheme.md",
            "signature": "94860320181333",
            "tags": [
            ]
        },
        {
            "attachment_folder": "",
            "created_time": "2022-12-31T10:17:57Z",
            "id": "20196",
            "modified_time": "2022-12-31T10:17:57Z",
            "name": "scheme86-fpga.md",
            "signature": "137517935365205",
            "tags": [
            ]
        },
        {
            "attachment_folder": "",
            "created_time": "2022-12-31T10:17:57Z",
            "id": "20197",
            "modified_time": "2022-12-31T10:17:57Z",
            "name": "The Little Schemer .md",
            "signature": "67093356612693",
            "tags": [
            ]
        },
        {
            "attachment_folder": "",
            "created_time": "2022-12-31T10:17:57Z",
            "id": "20198",
            "modified_time": "2022-12-31T10:17:57Z",
            "name": "Yet Another Scheme Tutorial Scheme.md",
            "signature": "130671757495381",
            "tags": [
            ]
        }
    ],
    "folders": [
    ],
    "id": "20193",
    "modified_time": "2022-12-31T10:17:57Z",
    "signature": "88228890676309",
    "version": 3
}
