{
    "created_time": "2022-12-31T10:18:05Z",
    "files": [
        {
            "attachment_folder": "",
            "created_time": "2022-12-31T10:18:05Z",
            "id": "22405",
            "modified_time": "2022-12-31T10:18:05Z",
            "name": "nLabs.md",
            "signature": "86210256047197",
            "tags": [
            ]
        },
        {
            "attachment_folder": "",
            "created_time": "2022-12-31T10:18:05Z",
            "id": "22406",
            "modified_time": "2022-12-31T10:18:05Z",
            "name": "tmp.md",
            "signature": "47821838355549",
            "tags": [
            ]
        },
        {
            "attachment_folder": "",
            "created_time": "2022-12-31T10:18:05Z",
            "id": "22407",
            "modified_time": "2022-12-31T10:18:05Z",
            "name": "一个大学生的数学笔记.md",
            "signature": "98854639766621",
            "tags": [
            ]
        },
        {
            "attachment_folder": "",
            "created_time": "2022-12-31T10:18:05Z",
            "id": "22408",
            "modified_time": "2022-12-31T10:18:05Z",
            "name": "互动数学.md",
            "signature": "107590603246685",
            "tags": [
            ]
        },
        {
            "attachment_folder": "",
            "created_time": "2022-12-31T10:18:05Z",
            "id": "22416",
            "modified_time": "2022-12-31T10:18:05Z",
            "name": "共鸣！.md",
            "signature": "87013414931549",
            "tags": [
            ]
        },
        {
            "attachment_folder": "",
            "created_time": "2022-12-31T10:18:05Z",
            "id": "22440",
            "modified_time": "2022-12-31T10:18:05Z",
            "name": "数学审美.md",
            "signature": "35894714174557",
            "tags": [
            ]
        }
    ],
    "folders": [
        {
            "name": "信息和香农信息论"
        },
        {
            "name": "几何"
        },
        {
            "name": "分析"
        },
        {
            "name": "皇冠上的明珠_人类智慧的荣光"
        },
        {
            "name": "离散pdfcdf应用数学凸优化运筹"
        },
        {
            "name": "统计概率"
        },
        {
            "name": "近世代数"
        },
        {
            "name": "集合论模型出发的计算机自动机"
        }
    ],
    "id": "22404",
    "modified_time": "2022-12-31T10:18:05Z",
    "signature": "20849443736669",
    "version": 3
}
