{
    "created_time": "2022-12-31T10:17:15Z",
    "files": [
        {
            "attachment_folder": "",
            "created_time": "2022-12-31T10:17:15Z",
            "id": "17773",
            "modified_time": "2022-12-31T10:17:15Z",
            "name": "conan、vcpkg.md",
            "signature": "113225600338987",
            "tags": [
            ]
        },
        {
            "attachment_folder": "",
            "created_time": "2022-12-31T10:17:15Z",
            "id": "17774",
            "modified_time": "2022-12-31T10:17:15Z",
            "name": "include头文件路径linux默认包含路径.md",
            "signature": "20986882690091",
            "tags": [
            ]
        }
    ],
    "folders": [
    ],
    "id": "17772",
    "modified_time": "2022-12-31T10:17:15Z",
    "signature": "97265501867051",
    "version": 3
}
