{
    "created_time": "2022-12-31T10:18:05Z",
    "files": [
        {
            "attachment_folder": "",
            "created_time": "2022-12-31T10:18:05Z",
            "id": "22442",
            "modified_time": "2022-12-31T10:18:05Z",
            "name": "abc猜想.md",
            "signature": "65590118059101",
            "tags": [
            ]
        }
    ],
    "folders": [
    ],
    "id": "22441",
    "modified_time": "2022-12-31T10:18:05Z",
    "signature": "86201666112605",
    "version": 3
}
