{
    "created_time": "2022-12-31T10:17:14Z",
    "files": [
        {
            "attachment_folder": "",
            "created_time": "2022-12-31T10:17:14Z",
            "id": "17703",
            "modified_time": "2022-12-31T10:17:14Z",
            "name": "array-Vector-Eigen转换矩阵格式.md",
            "signature": "29636946824234",
            "tags": [
            ]
        },
        {
            "attachment_folder": "",
            "created_time": "2022-12-31T10:17:14Z",
            "id": "17704",
            "modified_time": "2022-12-31T10:17:14Z",
            "name": "Eigen.md",
            "signature": "16271008599082",
            "tags": [
            ]
        },
        {
            "attachment_folder": "",
            "created_time": "2022-12-31T10:17:14Z",
            "id": "17705",
            "modified_time": "2022-12-31T10:17:14Z",
            "name": "Eigen常见错误.md",
            "signature": "77856544656426",
            "tags": [
            ]
        },
        {
            "attachment_folder": "",
            "created_time": "2022-12-31T10:17:14Z",
            "id": "17706",
            "modified_time": "2022-12-31T10:17:14Z",
            "name": "Eigen文档官方.md",
            "signature": "2007422209066",
            "tags": [
            ]
        },
        {
            "attachment_folder": "",
            "created_time": "2022-12-31T10:17:14Z",
            "id": "17707",
            "modified_time": "2022-12-31T10:17:14Z",
            "name": "ifndef可以解决编译阶段发生的重复定义问题，但不能解决链接阶段发生的重复定义问题.md",
            "signature": "16013310561322",
            "tags": [
            ]
        },
        {
            "attachment_folder": "",
            "created_time": "2022-12-31T10:17:14Z",
            "id": "17708",
            "modified_time": "2022-12-31T10:17:14Z",
            "name": "Pybind11-Eigen.md",
            "signature": "63966620421162",
            "tags": [
            ]
        },
        {
            "attachment_folder": "",
            "created_time": "2022-12-31T10:17:14Z",
            "id": "17709",
            "modified_time": "2022-12-31T10:17:14Z",
            "name": "Regex＿C.md",
            "signature": "105864026393642",
            "tags": [
            ]
        },
        {
            "attachment_folder": "",
            "created_time": "2022-12-31T10:17:14Z",
            "id": "17710",
            "modified_time": "2022-12-31T10:17:14Z",
            "name": "动态数组.md",
            "signature": "96565422197802",
            "tags": [
            ]
        },
        {
            "attachment_folder": "",
            "created_time": "2022-12-31T10:17:14Z",
            "id": "17711",
            "modified_time": "2022-12-31T10:17:14Z",
            "name": "千万别把你的stl 容器,模板容器在 dll 间传来传去 .  记住string也是千万别别把你的stl 容器,模板容器在 dll 间传来传去 .  记住string也是.md",
            "signature": "76482155121706",
            "tags": [
            ]
        },
        {
            "attachment_folder": "",
            "created_time": "2022-12-31T10:17:14Z",
            "id": "17712",
            "modified_time": "2022-12-31T10:17:14Z",
            "name": "好用的cpp矩阵库.md",
            "signature": "10399788305450",
            "tags": [
            ]
        },
        {
            "attachment_folder": "",
            "created_time": "2022-12-31T10:17:14Z",
            "id": "17713",
            "modified_time": "2022-12-31T10:17:14Z",
            "name": "英文检索少很多麻烦.md",
            "signature": "61462654487594",
            "tags": [
            ]
        },
        {
            "attachment_folder": "",
            "created_time": "2022-12-31T10:17:14Z",
            "id": "17714",
            "modified_time": "2022-12-31T10:17:14Z",
            "name": "读取一个未知大小的array二位数组.md",
            "signature": "28421471079466",
            "tags": [
            ]
        },
        {
            "attachment_folder": "",
            "created_time": "2022-12-31T10:17:14Z",
            "id": "17715",
            "modified_time": "2022-12-31T10:17:14Z",
            "name": "负无穷.md",
            "signature": "97982761405482",
            "tags": [
            ]
        }
    ],
    "folders": [
    ],
    "id": "17702",
    "modified_time": "2022-12-31T10:17:14Z",
    "signature": "119994468797482",
    "version": 3
}
