{
    "created_time": "2022-12-31T10:17:59Z",
    "files": [
        {
            "attachment_folder": "",
            "created_time": "2022-12-31T10:17:59Z",
            "id": "20681",
            "modified_time": "2022-12-31T10:17:59Z",
            "name": "ai-mit-cources.md",
            "signature": "36994225802327",
            "tags": [
            ]
        },
        {
            "attachment_folder": "",
            "created_time": "2022-12-31T10:17:59Z",
            "id": "20682",
            "modified_time": "2022-12-31T10:17:59Z",
            "name": "CMU15-410Operating System Design and Implementation_LectureNotes.md",
            "signature": "107285660568663",
            "tags": [
            ]
        },
        {
            "attachment_folder": "",
            "created_time": "2022-12-31T10:17:59Z",
            "id": "20683",
            "modified_time": "2022-12-31T10:17:59Z",
            "name": "CMU机器学习课程.md",
            "signature": "79754920201303",
            "tags": [
            ]
        },
        {
            "attachment_folder": "",
            "created_time": "2022-12-31T10:17:59Z",
            "id": "20684",
            "modified_time": "2022-12-31T10:17:59Z",
            "name": "CMU算法课程.md",
            "signature": "2862120701015",
            "tags": [
            ]
        },
        {
            "attachment_folder": "",
            "created_time": "2022-12-31T10:17:59Z",
            "id": "20685",
            "modified_time": "2022-12-31T10:17:59Z",
            "name": "CMU镇校神课.md",
            "signature": "32982726347863",
            "tags": [
            ]
        },
        {
            "attachment_folder": "",
            "created_time": "2022-12-31T10:17:59Z",
            "id": "20686",
            "modified_time": "2022-12-31T10:17:59Z",
            "name": "lynda网站显示中文字幕.md",
            "signature": "118443985603671",
            "tags": [
            ]
        },
        {
            "attachment_folder": "",
            "created_time": "2022-12-31T10:17:59Z",
            "id": "20687",
            "modified_time": "2022-12-31T10:17:59Z",
            "name": "MIT-CS.md",
            "signature": "119560677100631",
            "tags": [
            ]
        },
        {
            "attachment_folder": "",
            "created_time": "2022-12-31T10:17:59Z",
            "id": "20688",
            "modified_time": "2022-12-31T10:17:59Z",
            "name": "MIT_Youtube.md",
            "signature": "14613151222871",
            "tags": [
            ]
        },
        {
            "attachment_folder": "",
            "created_time": "2022-12-31T10:17:59Z",
            "id": "20689",
            "modified_time": "2022-12-31T10:17:59Z",
            "name": "MIT机器学习课程LectureNotes.md",
            "signature": "99279841528919",
            "tags": [
            ]
        },
        {
            "attachment_folder": "",
            "created_time": "2022-12-31T10:17:59Z",
            "id": "20690",
            "modified_time": "2022-12-31T10:17:59Z",
            "name": "Stanford斯坦福cs计算机慕课汇总.md",
            "signature": "100040050740311",
            "tags": [
            ]
        },
        {
            "attachment_folder": "",
            "created_time": "2022-12-31T10:17:59Z",
            "id": "20691",
            "modified_time": "2022-12-31T10:17:59Z",
            "name": "哈弗资源文档课程等.md",
            "signature": "7401901132887",
            "tags": [
            ]
        },
        {
            "attachment_folder": "",
            "created_time": "2022-12-31T10:17:59Z",
            "id": "20692",
            "modified_time": "2022-12-31T10:17:59Z",
            "name": "国内外免费公开课网站集合.md",
            "signature": "12336818555991",
            "tags": [
            ]
        },
        {
            "attachment_folder": "",
            "created_time": "2022-12-31T10:17:59Z",
            "id": "20693",
            "modified_time": "2022-12-31T10:17:59Z",
            "name": "斯科特杨.md",
            "signature": "126479869414487",
            "tags": [
            ]
        },
        {
            "attachment_folder": "",
            "created_time": "2022-12-31T10:17:59Z",
            "id": "20694",
            "modified_time": "2022-12-31T10:17:59Z",
            "name": "神经网络MIT.md",
            "signature": "130237965798487",
            "tags": [
            ]
        },
        {
            "attachment_folder": "",
            "created_time": "2022-12-31T10:17:59Z",
            "id": "20695",
            "modified_time": "2022-12-31T10:17:59Z",
            "name": "课程课件文件资料.md",
            "signature": "47903442734167",
            "tags": [
            ]
        }
    ],
    "folders": [
    ],
    "id": "20680",
    "modified_time": "2022-12-31T10:17:59Z",
    "signature": "123928658840663",
    "version": 3
}
