{
    "created_time": "2022-12-31T10:17:54Z",
    "files": [
        {
            "attachment_folder": "",
            "created_time": "2022-12-31T10:17:54Z",
            "id": "19291",
            "modified_time": "2022-12-31T10:17:54Z",
            "name": "数据库连接.mlx",
            "signature": "2329544756306",
            "tags": [
            ]
        }
    ],
    "folders": [
    ],
    "id": "19290",
    "modified_time": "2022-12-31T10:17:54Z",
    "signature": "21476508961874",
    "version": 3
}
