{
    "created_time": "2022-12-31T10:18:14Z",
    "files": [
        {
            "attachment_folder": "",
            "created_time": "2022-12-31T10:18:14Z",
            "id": "24710",
            "modified_time": "2022-12-31T10:18:14Z",
            "name": "99haskell面向问题求解.md",
            "signature": "74850067549286",
            "tags": [
            ]
        },
        {
            "attachment_folder": "",
            "created_time": "2022-12-31T10:18:14Z",
            "id": "24711",
            "modified_time": "2022-12-31T10:18:14Z",
            "name": "Haskell99题.md",
            "signature": "112276412566630",
            "tags": [
            ]
        },
        {
            "attachment_folder": "",
            "created_time": "2022-12-31T10:18:14Z",
            "id": "24712",
            "modified_time": "2022-12-31T10:18:14Z",
            "name": "Pandoc.md",
            "signature": "12500027313254",
            "tags": [
            ]
        }
    ],
    "folders": [
    ],
    "id": "24709",
    "modified_time": "2022-12-31T10:18:14Z",
    "signature": "53018748783718",
    "version": 3
}
