{
    "created_time": "2022-12-31T10:18:14Z",
    "files": [
        {
            "attachment_folder": "",
            "created_time": "2022-12-31T10:18:14Z",
            "id": "24716",
            "modified_time": "2022-12-31T10:18:14Z",
            "name": "Happy.md",
            "signature": "133566565452902",
            "tags": [
            ]
        },
        {
            "attachment_folder": "",
            "created_time": "2022-12-31T10:18:14Z",
            "id": "24717",
            "modified_time": "2022-12-31T10:18:14Z",
            "name": "编译原理.md",
            "signature": "45700124511334",
            "tags": [
            ]
        },
        {
            "attachment_folder": "",
            "created_time": "2022-12-31T10:18:14Z",
            "id": "24718",
            "modified_time": "2022-12-31T10:18:14Z",
            "name": "自己动手写编译器.md",
            "signature": "4859280493670",
            "tags": [
            ]
        }
    ],
    "folders": [
    ],
    "id": "24715",
    "modified_time": "2022-12-31T10:18:14Z",
    "signature": "84539513769062",
    "version": 3
}
